dotenv_credential_helper/__init__.py
dotenv_credential_helper-0.0.1.dist-info/WHEEL
dotenv_credential_helper-0.0.1.dist-info/METADATA
dotenv_credential_helper-0.0.1.dist-info/RECORD
